cdfwriter/__init__.py
cdfwriter/interface.py
cdfwriter-1.2.3.dist-info/licenses/LICENSE.txt
cdfwriter-1.2.3.dist-info/METADATA
cdfwriter-1.2.3.dist-info/WHEEL
cdfwriter-1.2.3.dist-info/top_level.txt
cdfwriter-1.2.3.dist-info/RECORD
