Metadata-Version: 2.4
Name: cdfwriter
Version: 1.2.3
Summary: A small and simple package for writing CDF files
Home-page: http://github.com/joeymukherjee/cdfwriter
Author: Joey Mukherjee
Author-email: Joey Mukherjee <joey.mukherjee@yahoo.com>, Carrie Gonzalez <carrie.gonzalez@swri.org>
License-Expression: MIT AND (Apache-2.0 OR BSD-2-Clause)
Project-URL: Homepage, https://github.com/joeymukherjee/cdfwriter
Project-URL: Bug Tracker, https://github.com/joeymukherjee/cdfwriter/issues
Classifier: Programming Language :: Python :: 3
Classifier: Operating System :: OS Independent
Requires-Python: >=3.7
License-File: LICENSE.txt
Requires-Dist: numpy
Requires-Dist: spacepy
Provides-Extra: tests
Requires-Dist: pytest; extra == "tests"
Requires-Dist: flake8; extra == "tests"
Dynamic: license-file
